iamai/adapter/mirai/__init__.py
iamai/adapter/mirai/config.py
iamai/adapter/mirai/event/__init__.py
iamai/adapter/mirai/event/base.py
iamai/adapter/mirai/event/mate.py
iamai/adapter/mirai/event/message.py
iamai/adapter/mirai/event/notice.py
iamai/adapter/mirai/event/request.py
iamai/adapter/mirai/exceptions.py
iamai/adapter/mirai/message.py
iamai_adapter_mirai-3.2.3.dist-info/LICENSE
iamai_adapter_mirai-3.2.3.dist-info/METADATA
iamai_adapter_mirai-3.2.3.dist-info/WHEEL
iamai_adapter_mirai-3.2.3.dist-info/RECORD
