Metadata-Version: 2.1
Name: iamai-adapter-mirai
Version: 3.2.3
Summary: Mirai adapter for iamai.
Home-page: https://retrofor.space/
License: GPL-3.0 License
Keywords: bot,chatbot,qq,qqbot,mirai
Author: 简律纯
Author-email: i@jyunko.cn
Requires-Python: >=3.8,<4.0
Classifier: Development Status :: 3 - Alpha
Classifier: Framework :: AsyncIO
Classifier: Framework :: Robot Framework
Classifier: Framework :: Robot Framework :: Library
Classifier: License :: OSI Approved :: MIT License
Classifier: License :: Other/Proprietary License
Classifier: Operating System :: OS Independent
Classifier: Programming Language :: Python :: 3
Classifier: Programming Language :: Python :: 3.8
Classifier: Programming Language :: Python :: 3.9
Classifier: Programming Language :: Python :: 3.10
Classifier: Programming Language :: Python :: 3.11
Classifier: Topic :: Communications :: Chat
Requires-Dist: iamai (>=3.2)
Project-URL: Documentation, https://iamai.retrofor.space/
Project-URL: Repository, https://github.com/retrofor/iamai
